[
  {
    "choices": [
      {
        "content": {
          "type": "T",
          "text": "a large, colorful sculpture in a park",
          "style": {
            "textStyle": "string"
          }
        },
        "index": 0
      },
      {
        "content": {
          "type": "T",
          "text": "a small, gray statue in a museum",
          "style": {
            "textStyle": "string"
          }
        },
        "index": 1
      },
      {
        "content": {
          "type": "T",
          "text": "a painting hanging in a gallery",
          "style": {
            "textStyle": "string"
          }
        },
        "index": 2
      },
      {
        "content": {
          "type": "T",
          "text": "a black and white photograph on a wall",
          "style": {
            "textStyle": "string"
          }
        },
        "index": 3
      }
    ],
    "materials": [
      {
        "content": {
          "type": "T",
          "text": "M: Have you seen the new art installation in the park?\nW: Yes, the giant colorful sculpture is truly eye-catching.",
          "style": {
            "textStyle": "string"
          }
        },
        "index": 0
      }
    ],
    "ask": {
      "type": "T",
      "text": "Describe an image reflecting the situation of the dialogue.",
      "style": {
        "textStyle": "string"
      }
    }
  },
  {
    "choices": [
      {
        "content": {
          "type": "T",
          "text": "a puppy chewing on a shoe",
          "style": {
            "textStyle": "string"
          }
        },
        "index": 0
      },
      {
        "content": {
          "type": "T",
          "text": "a cat sleeping on a couch",
          "style": {
            "textStyle": "string"
          }
        },
        "index": 1
      },
      {
        "content": {
          "type": "T",
          "text": "a dog fetching a ball",
          "style": {
            "textStyle": "string"
          }
        },
        "index": 2
      },
      {
        "content": {
          "type": "T",
          "text": "a rabbit eating a carrot",
          "style": {
            "textStyle": "string"
          }
        },
        "index": 3
      }
    ],
    "materials": [
      {
        "content": {
          "type": "T",
          "text": "W: I heard you got a new puppy. How's that going?\nM: It's adorable, but it chews on everything, including my shoes!",
          "style": {
            "textStyle": "string"
          }
        },
        "index": 0
      }
    ],
    "ask": {
      "type": "T",
      "text": "Describe an image reflecting the situation of the dialogue.",
      "style": {
        "textStyle": "string"
      }
    }
  },
  {
    "choices": [
      {
        "content": {
          "type": "T",
          "text": "a night sky with lightning",
          "style": {
            "textStyle": "string"
          }
        },
        "index": 0
      },
      {
        "content": {
          "type": "T",
          "text": "a clear blue sky with sunshine",
          "style": {
            "textStyle": "string"
          }
        },
        "index": 1
      },
      {
        "content": {
          "type": "T",
          "text": "a field with gentle rain",
          "style": {
            "textStyle": "string"
          }
        },
        "index": 2
      },
      {
        "content": {
          "type": "T",
          "text": "a sunset over a calm lake",
          "style": {
            "textStyle": "string"
          }
        },
        "index": 3
      }
    ],
    "materials": [
      {
        "content": {
          "type": "T",
          "text": "M: Did you notice the storm last night? It was quite intense.\nW: Yes, the thunder and lightning kept me awake for hours.",
          "style": {
            "textStyle": "string"
          }
        },
        "index": 0
      }
    ],
    "ask": {
      "type": "T",
      "text": "Describe an image reflecting the situation of the dialogue.",
      "style": {
        "textStyle": "string"
      }
    }
  },
  {
    "choices": [
      {
        "content": {
          "type": "T",
          "text": "a person with a unique hairstyle",
          "style": {
            "textStyle": "string"
          }
        },
        "index": 0
      },
      {
        "content": {
          "type": "T",
          "text": "a person wearing a hat",
          "style": {
            "textStyle": "string"
          }
        },
        "index": 1
      },
      {
        "content": {
          "type": "T",
          "text": "a person with long, straight hair",
          "style": {
            "textStyle": "string"
          }
        },
        "index": 2
      },
      {
        "content": {
          "type": "T",
          "text": "a person with a ponytail",
          "style": {
            "textStyle": "string"
          }
        },
        "index": 3
      }
    ],
    "materials": [
      {
        "content": {
          "type": "T",
          "text": "W: Your new hairstyle looks fantastic!\nM: Thank you! I decided to try something bold and different.",
          "style": {
            "textStyle": "string"
          }
        },
        "index": 0
      }
    ],
    "ask": {
      "type": "T",
      "text": "Describe an image reflecting the situation of the dialogue.",
      "style": {
        "textStyle": "string"
      }
    }
  },
  {
    "choices": [
      {
        "content": {
          "type": "T",
          "text": "a bouquet of colorful flowers",
          "style": {
            "textStyle": "string"
          }
        },
        "index": 0
      },
      {
        "content": {
          "type": "T",
          "text": "a wrapped box with a bow",
          "style": {
            "textStyle": "string"
          }
        },
        "index": 1
      },
      {
        "content": {
          "type": "T",
          "text": "a pair of elegant earrings",
          "style": {
            "textStyle": "string"
          }
        },
        "index": 2
      },
      {
        "content": {
          "type": "T",
          "text": "a book with a leather cover",
          "style": {
            "textStyle": "string"
          }
        },
        "index": 3
      }
    ],
    "materials": [
      {
        "content": {
          "type": "T",
          "text": "M: I need to buy a gift for Sarah's birthday.\nW: How about a beautiful bouquet of flowers?",
          "style": {
            "textStyle": "string"
          }
        },
        "index": 0
      }
    ],
    "ask": {
      "type": "T",
      "text": "Describe an image reflecting the situation of the dialogue.",
      "style": {
        "textStyle": "string"
      }
    }
  }
]