[
  {
    "choices": [
      {
        "content": {
          "type": "T",
          "text": "apple",
          "style": {
            "textStyle": "string"
          }
        },
        "index": 0
      },
      {
        "content": {
          "type": "T",
          "text": "grape",
          "style": {
            "textStyle": "string"
          }
        },
        "index": 1
      },
      {
        "content": {
          "type": "T",
          "text": "berry",
          "style": {
            "textStyle": "string"
          }
        },
        "index": 2
      },
      {
        "content": {
          "type": "T",
          "text": "peach",
          "style": {
            "textStyle": "string"
          }
        },
        "index": 3
      }
    ],
    "materials": [
      {
        "content": {
          "type": "T",
          "text": "I am small and round. I grow on trees. My color is red or green. People eat me in pies and juice. I am sweet and crunchy.",
          "style": {
            "textStyle": "string"
          }
        },
        "index": 0
      }
    ],
    "ask": {
      "type": "T",
      "text": "What am I?",
      "style": {
        "textStyle": "string"
      }
    }
  },
  {
    "choices": [
      {
        "content": {
          "type": "T",
          "text": "Monday",
          "style": {
            "textStyle": "string"
          }
        },
        "index": 0
      },
      {
        "content": {
          "type": "T",
          "text": "Tuesday",
          "style": {
            "textStyle": "string"
          }
        },
        "index": 1
      },
      {
        "content": {
          "type": "T",
          "text": "Wednesday",
          "style": {
            "textStyle": "string"
          }
        },
        "index": 2
      },
      {
        "content": {
          "type": "T",
          "text": "Thursday",
          "style": {
            "textStyle": "string"
          }
        },
        "index": 3
      }
    ],
    "materials": [
      {
        "content": {
          "type": "T",
          "text": "Today is Monday. I have a math test. I studied all weekend. I feel ready. After school, I will play soccer with my friends.",
          "style": {
            "textStyle": "string"
          }
        },
        "index": 0
      }
    ],
    "ask": {
      "type": "T",
      "text": "What day is it today?",
      "style": {
        "textStyle": "string"
      }
    }
  },
  {
    "choices": [
      {
        "content": {
          "type": "T",
          "text": "math",
          "style": {
            "textStyle": "string"
          }
        },
        "index": 0
      },
      {
        "content": {
          "type": "T",
          "text": "music",
          "style": {
            "textStyle": "string"
          }
        },
        "index": 1
      },
      {
        "content": {
          "type": "T",
          "text": "art",
          "style": {
            "textStyle": "string"
          }
        },
        "index": 2
      },
      {
        "content": {
          "type": "T",
          "text": "science",
          "style": {
            "textStyle": "string"
          }
        },
        "index": 3
      }
    ],
    "materials": [
      {
        "content": {
          "type": "T",
          "text": "Today is Monday. I have a math test. I studied all weekend. I feel ready. After school, I will play soccer with my friends.",
          "style": {
            "textStyle": "string"
          }
        },
        "index": 0
      }
    ],
    "ask": {
      "type": "T",
      "text": "What subject is the test?",
      "style": {
        "textStyle": "string"
      }
    }
  },
  {
    "choices": [
      {
        "content": {
          "type": "T",
          "text": "Whiskers",
          "style": {
            "textStyle": "string"
          }
        },
        "index": 0
      },
      {
        "content": {
          "type": "T",
          "text": "Fluffy",
          "style": {
            "textStyle": "string"
          }
        },
        "index": 1
      },
      {
        "content": {
          "type": "T",
          "text": "Snowy",
          "style": {
            "textStyle": "string"
          }
        },
        "index": 2
      },
      {
        "content": {
          "type": "T",
          "text": "Mittens",
          "style": {
            "textStyle": "string"
          }
        },
        "index": 3
      }
    ],
    "materials": [
      {
        "content": {
          "type": "T",
          "text": "Lucy has a pet cat named Whiskers. Whiskers is white and fluffy. He likes to chase balls. Lucy feeds him every morning.",
          "style": {
            "textStyle": "string"
          }
        },
        "index": 0
      }
    ],
    "ask": {
      "type": "T",
      "text": "What is Lucy's pet's name?",
      "style": {
        "textStyle": "string"
      }
    }
  },
  {
    "choices": [
      {
        "content": {
          "type": "T",
          "text": "white",
          "style": {
            "textStyle": "string"
          }
        },
        "index": 0
      },
      {
        "content": {
          "type": "T",
          "text": "black",
          "style": {
            "textStyle": "string"
          }
        },
        "index": 1
      },
      {
        "content": {
          "type": "T",
          "text": "brown",
          "style": {
            "textStyle": "string"
          }
        },
        "index": 2
      },
      {
        "content": {
          "type": "T",
          "text": "gray",
          "style": {
            "textStyle": "string"
          }
        },
        "index": 3
      }
    ],
    "materials": [
      {
        "content": {
          "type": "T",
          "text": "Lucy has a pet cat named Whiskers. Whiskers is white and fluffy. He likes to chase balls. Lucy feeds him every morning.",
          "style": {
            "textStyle": "string"
          }
        },
        "index": 0
      }
    ],
    "ask": {
      "type": "T",
      "text": "What color is Whiskers?",
      "style": {
        "textStyle": "string"
      }
    }
  },
  {
    "choices": [
      {
        "content": {
          "type": "T",
          "text": "sandwiches",
          "style": {
            "textStyle": "string"
          }
        },
        "index": 0
      },
      {
        "content": {
          "type": "T",
          "text": "cookies",
          "style": {
            "textStyle": "string"
          }
        },
        "index": 1
      },
      {
        "content": {
          "type": "T",
          "text": "candy",
          "style": {
            "textStyle": "string"
          }
        },
        "index": 2
      },
      {
        "content": {
          "type": "T",
          "text": "cake",
          "style": {
            "textStyle": "string"
          }
        },
        "index": 3
      }
    ],
    "materials": [
      {
        "content": {
          "type": "T",
          "text": "Sam's family is having a picnic. They bring sandwiches, fruit, and juice. Sam plays on the swings. His sister flies a kite.",
          "style": {
            "textStyle": "string"
          }
        },
        "index": 0
      }
    ],
    "ask": {
      "type": "T",
      "text": "What does Sam's family bring to the picnic?",
      "style": {
        "textStyle": "string"
      }
    }
  },
  {
    "choices": [
      {
        "content": {
          "type": "T",
          "text": "swings",
          "style": {
            "textStyle": "string"
          }
        },
        "index": 0
      },
      {
        "content": {
          "type": "T",
          "text": "slide",
          "style": {
            "textStyle": "string"
          }
        },
        "index": 1
      },
      {
        "content": {
          "type": "T",
          "text": "seesaw",
          "style": {
            "textStyle": "string"
          }
        },
        "index": 2
      },
      {
        "content": {
          "type": "T",
          "text": "merry-go-round",
          "style": {
            "textStyle": "string"
          }
        },
        "index": 3
      }
    ],
    "materials": [
      {
        "content": {
          "type": "T",
          "text": "Sam's family is having a picnic. They bring sandwiches, fruit, and juice. Sam plays on the swings. His sister flies a kite.",
          "style": {
            "textStyle": "string"
          }
        },
        "index": 0
      }
    ],
    "ask": {
      "type": "T",
      "text": "What does Sam play on?",
      "style": {
        "textStyle": "string"
      }
    }
  },
  {
    "choices": [
      {
        "content": {
          "type": "T",
          "text": "bicycle",
          "style": {
            "textStyle": "string"
          }
        },
        "index": 0
      },
      {
        "content": {
          "type": "T",
          "text": "scooter",
          "style": {
            "textStyle": "string"
          }
        },
        "index": 1
      },
      {
        "content": {
          "type": "T",
          "text": "skateboard",
          "style": {
            "textStyle": "string"
          }
        },
        "index": 2
      },
      {
        "content": {
          "type": "T",
          "text": "rollerblades",
          "style": {
            "textStyle": "string"
          }
        },
        "index": 3
      }
    ],
    "materials": [
      {
        "content": {
          "type": "T",
          "text": "I have two wheels. You can ride me. I have a seat and handlebars. People wear helmets when they use me. I am faster than walking.",
          "style": {
            "textStyle": "string"
          }
        },
        "index": 0
      }
    ],
    "ask": {
      "type": "T",
      "text": "What am I?",
      "style": {
        "textStyle": "string"
      }
    }
  }
]